scrapy_cloud_browser/__about__.py
scrapy_cloud_browser/__init__.py
scrapy_cloud_browser/download_handler.py
scrapy_cloud_browser/extension.py
scrapy_cloud_browser/schemas.py
scrapy_cloud_browser/scenarist/__init__.py
scrapy_cloud_browser/scenarist/browser.py
scrapy_cloud_browser/scenarist/connection.py
scrapy_cloud_browser/scenarist/errors.py
scrapy_cloud_browser/scenarist/page.py
scrapy_cloud_browser-0.1.1.dist-info/LICENSE.txt
scrapy_cloud_browser-0.1.1.dist-info/METADATA
scrapy_cloud_browser-0.1.1.dist-info/WHEEL
scrapy_cloud_browser-0.1.1.dist-info/top_level.txt
scrapy_cloud_browser-0.1.1.dist-info/RECORD
