Metadata-Version: 2.2
Name: scrapy-cloud-browser
Version: 0.1.1
Summary: A Scrapy extension that integrates with https://surfsky.io
Author-email: "Surfsky.io" <hello@surfsky.io>
License: MIT
Project-URL: Documentation, https://github.com/cloudbrowser/scrapy-cloud-browser#readme
Project-URL: Issues, https://github.com/cloudbrowser/scrapy-cloud-browser/issues
Project-URL: Source, https://github.com/cloudbrowser/scrapy-cloud-browser
Project-URL: Homepage, https://github.com/cloudbrowser/scrapy-cloud-browser
Project-URL: Bug Tracker, https://github.com/cloudbrowser/scrapy-cloud-browser/issues
Classifier: Development Status :: 4 - Beta
Classifier: Programming Language :: Python
Classifier: Programming Language :: Python :: 3.7
Classifier: Programming Language :: Python :: 3.8
Classifier: Programming Language :: Python :: 3.9
Classifier: Programming Language :: Python :: 3.10
Classifier: Programming Language :: Python :: 3.11
Classifier: Programming Language :: Python :: 3.12
Classifier: Programming Language :: Python :: Implementation :: CPython
Classifier: Programming Language :: Python :: Implementation :: PyPy
Classifier: License :: OSI Approved :: MIT License
Classifier: Operating System :: OS Independent
Requires-Python: >=3.9
License-File: LICENSE.txt
Requires-Dist: httpx
Requires-Dist: pydantic>=2.10
Requires-Dist: websockets
Requires-Dist: scrapy~=2.12.0
Requires-Dist: anyio
